Changelog.txt
LICENSE.txt
MANIFEST.in
README.txt
distribute_setup.py
setup.py
Tests/README.txt
Tests/_common.py
Tests/runtests.py
Tests/testinspect.py
Tests/testprocess.py
Tests/testsignal.py
Tests/testutil.py
Tests/test_testing/__init__.py
Tests/test_testing/_common.py
Tests/test_testing/testmock.py
Tests/testqtgui/__init__.py
Tests/testqtgui/_common.py
Tests/testqtgui/testapplication.py
Tests/testqtgui/testmodels.py
Tests/testqtgui/testutil.py
Tests/testqtgui/testwidgets.py
srllib/__init__.py
srllib/_common.py
srllib/error.py
srllib/inspect.py
srllib/process.py
srllib/signal.py
srllib/threading.py
srllib/util.py
srllib.egg-info/PKG-INFO
srllib.egg-info/SOURCES.txt
srllib.egg-info/dependency_links.txt
srllib.egg-info/top_level.txt
srllib/qtgui/__init__.py
srllib/qtgui/_application.py
srllib/qtgui/_common.py
srllib/qtgui/_signal.py
srllib/qtgui/models.py
srllib/qtgui/util.py
srllib/qtgui/widgets.py
srllib/testing/__init__.py
srllib/testing/_ifacemock.py
srllib/testing/coverage.py
srllib/testing/mock.py
srllib/testing/qtgui/__init__.py
srllib/testing/qtgui/mock.py
srllib/testing/qtgui/mocks.py