Metadata-Version: 1.1
Name: srllib
Version: 0.5.6
Summary: General Python application library.
Home-page: http://code.google.com/p/srl-python-lib
Author: Arve Knudsen
Author-email: arve.knudsen@gmail.com
License: MIT
Platform: All
Classifier: Development Status :: 5 - Production/Stable
Classifier: Intended Audience :: Developers
Classifier: Programming Language :: Python :: 2
Classifier: Operating System :: OS Independent
Classifier: Topic :: Software Development :: Libraries
